DSGRN/BlowupGraph.py
DSGRN/BooleanParameterNeighbors.py
DSGRN/DrawParameterGraph.py
DSGRN/EquilibriumCells.py
DSGRN/EssentialParameterNeighbors.py
DSGRN/Graphics.py
DSGRN/MorseGraphIsomorphism.py
DSGRN/ParameterFromSample.py
DSGRN/ParameterPartialOrders.py
DSGRN/SaveDatabaseJSON.py
DSGRN/Signatures.py
DSGRN/SubdomainGraph.py
DSGRN/__init__.py
DSGRN/_dsgrn.cpython-313-x86_64-linux-gnu.so
DSGRN/Query/AlignmentGraph.py
DSGRN/Query/BistableQuery.py
DSGRN/Query/ComputeSingleGeneQuery.py
DSGRN/Query/Database.py
DSGRN/Query/DoubleFixedPointQuery.py
DSGRN/Query/FixedPointTables.py
DSGRN/Query/Graph.py
DSGRN/Query/Hexcodes.py
DSGRN/Query/HysteresisQuery.py
DSGRN/Query/InducibilityQuery.py
DSGRN/Query/Logging.py
DSGRN/Query/MonostableFixedPointQuery.py
DSGRN/Query/MonostableQuery.py
DSGRN/Query/MultistableQuery.py
DSGRN/Query/NstableQuery.py
DSGRN/Query/PhenotypeQuery.py
DSGRN/Query/PosetOfExtrema.py
DSGRN/Query/SingleFixedPointQuery.py
DSGRN/Query/SingleGeneQuery.py
DSGRN/Query/StableFCQuery.py
DSGRN/Query/__init__.py
DSGRN/Resources/CAD/1_1_1.json
DSGRN/Resources/CAD/1_2_1.json
DSGRN/Resources/CAD/1_3_1.json
DSGRN/Resources/CAD/1_4_1.json
DSGRN/Resources/CAD/1_5_1.json
DSGRN/Resources/CAD/1_6_1.json
DSGRN/Resources/CAD/1_7_1.json
DSGRN/Resources/CAD/2_1_1_1.json
DSGRN/Resources/CAD/2_1_2.json
DSGRN/Resources/CAD/2_2_1_1.json
DSGRN/Resources/CAD/2_2_2.json
DSGRN/Resources/CAD/2_3_1_1.json
DSGRN/Resources/CAD/2_3_2.json
DSGRN/Resources/CAD/2_4_1_1.json
DSGRN/Resources/CAD/2_4_2.json
DSGRN/Resources/CAD/2_5_1_1.json
DSGRN/Resources/CAD/2_5_2.json
DSGRN/Resources/CAD/2_6_1_1.json
DSGRN/Resources/CAD/2_6_2.json
DSGRN/Resources/CAD/2_7_1_1.json
DSGRN/Resources/CAD/2_7_2.json
DSGRN/Resources/CAD/3_1_1_1_1.json
DSGRN/Resources/CAD/3_1_1_2.json
DSGRN/Resources/CAD/3_1_3.json
DSGRN/Resources/CAD/3_2_1_1_1.json
DSGRN/Resources/CAD/3_2_1_2.json
DSGRN/Resources/CAD/3_2_3.json
DSGRN/Resources/CAD/3_3_1_1_1.json
dsgrn-1.9.1.dist-info/METADATA
dsgrn-1.9.1.dist-info/WHEEL
dsgrn-1.9.1.dist-info/entry_points.txt
dsgrn-1.9.1.dist-info/RECORD
dsgrn-1.9.1.dist-info/licenses/LICENSE
