Metadata-Version: 2.4
Name: DSGRN
Version: 1.9.1
Summary: DSGRN (Dynamic Signatures Generated by Regulatory Networks)
Home-page: https://github.com/marciogameiro/DSGRN
Author: Marcio Gameiro
Author-email: marciogameiro@gmail.com
License-File: LICENSE
Requires-Dist: scipy
Requires-Dist: matplotlib
Requires-Dist: numpy
Requires-Dist: graphviz
Requires-Dist: progressbar2
Requires-Dist: pychomp2
Provides-Extra: mpi
Requires-Dist: mpi4py; extra == "mpi"
Dynamic: author
Dynamic: author-email
Dynamic: description
Dynamic: description-content-type
Dynamic: home-page
Dynamic: license-file
Dynamic: provides-extra
Dynamic: requires-dist
Dynamic: summary
